gatherstockdata.py
gatherstockdata-0.0.1.dist-info/LICENSE.txt
gatherstockdata-0.0.1.dist-info/METADATA
gatherstockdata-0.0.1.dist-info/WHEEL
gatherstockdata-0.0.1.dist-info/top_level.txt
gatherstockdata-0.0.1.dist-info/RECORD
