Metadata-Version: 2.1
Name: gatherstockdata
Version: 0.0.1
Summary: Gather Stock data
Author: Lucas Rimfrost
Author-email: lucas.rimfrost@gmail.com
Classifier: Programming Language :: Python :: 3.9
Classifier: Programming Language :: Python :: 3.10
Classifier: Programming Language :: Python :: 3.11
Classifier: License :: OSI Approved :: GNU General Public License v2 or later (GPLv2+)
Classifier: Operating System :: OS Independent
License-File: LICENSE.txt
Requires-Dist: pandas
Requires-Dist: mplfinance
Requires-Dist: requests
Requires-Dist: bs4
Provides-Extra: dev
Requires-Dist: pytest (>=3.7) ; extra == 'dev'
